{
  "brand": "Apple",
  "name": "iPhone 17 Pro Max",
  "image": "/iphones/Iphone-15.png",
  "order": 40,
  "active": true,
  "repairs": [
    {
      "serviceKey": "recond",
      "price": 190
    },
    {
      "serviceKey": "screen",
      "price": 445
    },
    {
      "serviceKey": "back",
      "price": 150
    },
    {
      "serviceKey": "battery",
      "price": 95
    },
    {
      "serviceKey": "camera",
      "price": 175
    },
    {
      "serviceKey": "charge",
      "price": 160
    }
  ]
}
